TuModeloDeClientes_Navarro/__init__.py
TuModeloDeClientes_Navarro/__main__.py
TuModeloDeClientes_Navarro/main.py
TuModeloDeClientes_Navarro/paquete1/__init__.py
TuModeloDeClientes_Navarro/paquete1/modulo1.py
TuModeloDeClientes_Navarro/paquete1/modulo2.py
TuModeloDeClientes_Navarro-4.0.3.dist-info/METADATA
TuModeloDeClientes_Navarro-4.0.3.dist-info/WHEEL
TuModeloDeClientes_Navarro-4.0.3.dist-info/entry_points.txt
TuModeloDeClientes_Navarro-4.0.3.dist-info/top_level.txt
TuModeloDeClientes_Navarro-4.0.3.dist-info/RECORD
