Metadata-Version: 2.1
Name: TuModeloDeClientes-Navarro
Version: 4.0.3
Summary: Modelo de clientes para practicar Herencia, modulos y polimorfismo en Python
Author: Juan Navarro
